jinja_docker_compose/__init__.py
jinja_docker_compose/__version__.py
jinja_docker_compose/cli.py
jinja_docker_compose/jinja_docker_compose.py
jinja_docker_compose-2.0.2.dist-info/entry_points.txt
jinja_docker_compose-2.0.2.dist-info/WHEEL
jinja_docker_compose-2.0.2.dist-info/METADATA
jinja_docker_compose-2.0.2.dist-info/RECORD
