Metadata-Version: 2.1
Name: jinja-docker-compose
Version: 2.0.2
Summary: Enables jinja like preposessing of docker-compose files.
Home-page: https://github.com/MorganLindqvist/jinja-compose/blob/master/README.md
License: MIT
Author: Morgan
Author-email: Morgan@quzed.com
Requires-Python: >=3.7,<4.0
Classifier: License :: OSI Approved :: MIT License
Classifier: Programming Language :: Python :: 3
Classifier: Programming Language :: Python :: 3.7
Classifier: Programming Language :: Python :: 3.8
Classifier: Programming Language :: Python :: 3.9
Classifier: Programming Language :: Python :: 3.10
Classifier: Programming Language :: Python :: 3.11
Requires-Dist: Jinja2 (>=3.1.2,<4.0.0)
Requires-Dist: PyYAML (>=5.4.1,<6.0.0)
Requires-Dist: bcrypt (>=3.2.2,<4.0.0)
Requires-Dist: docker-compose (>=1.29.2,<2.0.0)
Project-URL: Repository, https://github.com/MorganLindqvist/jinja-compose
